src/app_demo/hdl/app_demo_top.vhd
-------------------------------------------------------------------------------
--          ____  _____________  __                                          --
--         / __ \/ ____/ ___/\ \/ /                 _   _   _                --
--        / / / / __/  \__ \  \  /                 / \ / \ / \               --
--       / /_/ / /___ ___/ /  / /               = ( M | S | K )=             --
--      /_____/_____//____/  /_/                   \_/ \_/ \_/               --
--                                                                           --
-------------------------------------------------------------------------------
-- Copyright (c) 2020 DESY
-------------------------------------------------------------------------------
--! @brief   Basic Example for FWK Module
--! @created 2020-01-30
-------------------------------------------------------------------------------
--! Description:
--! Simple Entity that creates a 32 bit counter with active high reset
-------------------------------------------------------------------------------

library ieee;
use ieee.std_logic_1164.all;
use ieee.numeric_std.all;

entity app_demo_top is
port( 
  pi_clock : in std_logic;
  pi_reset : in std_logic;
  po_counter : out std_logic_vector(31 downto 0)
);
end app_demo_top;

architecture behavioral of app_demo_top is
  signal counter : unsigned(31 downto 0);
begin

  po_counter <= std_logic_vector(counter);

  process(pi_clock) begin 
    if rising_edge(pi_clock) then 
      if pi_reset = '1' then 
        counter <= (others => '0');
      else
        counter <= counter + 2;
      end if;
    end if;
  end process;
  
end behavioral;

out/demo_cocotb_default/demo_cocotb_default_0.0.0-0-g20000000-LIC-174760.bnl.gov_test_counter.vcd
$date
  Fri Nov 15 17:10:41 2024
$end
$version
  GHDL v0
$end
$timescale
  1 ps
$end
$scope module standard $end
$upscope $end
$scope module std_logic_1164 $end
$upscope $end
$scope module numeric_std $end
$upscope $end
$scope module app_demo_top $end
$var reg 1 ! pi_clock $end
$var reg 1 " pi_reset $end
$var reg 32 # po_counter[31:0] $end
$var reg 32 $ counter[31:0] $end
$upscope $end
$enddefinitions $end
#0
0!
1"
bUUUUUUUUUUUUUUUUUUUUUUUUUUUUUUUU #
bUUUUUUUUUUUUUUUUUUUUUUUUUUUUUUUU $
#25000
1!
0"
b00000000000000000000000000000000 #
b00000000000000000000000000000000 $
#50000
0!
#75000
1!
b00000000000000000000000000000001 #
b00000000000000000000000000000001 $
#100000
0!
#125000
1!
b00000000000000000000000000000010 #
b00000000000000000000000000000010 $
#150000
0!
#175000
1!
b00000000000000000000000000000011 #
b00000000000000000000000000000011 $
#200000
0!
#225000
1!
b00000000000000000000000000000100 #
b00000000000000000000000000000100 $
#250000
0!
#275000
1!
b00000000000000000000000000000101 #
b00000000000000000000000000000101 $
#300000
0!
#325000
1!
b00000000000000000000000000000110 #
b00000000000000000000000000000110 $
#350000
0!
#375000
1!
b00000000000000000000000000000111 #
b00000000000000000000000000000111 $
#400000
0!
#425000
1!
b00000000000000000000000000001000 #
b00000000000000000000000000001000 $
#450000
0!
#475000
1!
b00000000000000000000000000001001 #
b00000000000000000000000000001001 $
#500000
0!
#525000
1!
b00000000000000000000000000001010 #
b00000000000000000000000000001010 $
#550000
0!
#575000
1!
b00000000000000000000000000001011 #
b00000000000000000000000000001011 $
#600000
0!
#625000
1!
b00000000000000000000000000001100 #
b00000000000000000000000000001100 $
#650000
0!
#675000
1!
b00000000000000000000000000001101 #
b00000000000000000000000000001101 $
#700000
0!
#725000
1!
b00000000000000000000000000001110 #
b00000000000000000000000000001110 $
#750000
0!
#775000
1!
b00000000000000000000000000001111 #
b00000000000000000000000000001111 $
#800000
0!
#825000
1!
b00000000000000000000000000010000 #
b00000000000000000000000000010000 $
#850000
0!
#875000
1!
b00000000000000000000000000010001 #
b00000000000000000000000000010001 $
#900000
0!
#925000
1!
b00000000000000000000000000010010 #
b00000000000000000000000000010010 $
#950000
0!
#975000
1!
b00000000000000000000000000010011 #
b00000000000000000000000000010011 $
#1000000
0!
#1025000
1!
b00000000000000000000000000010100 #
b00000000000000000000000000010100 $
#1050000
0!
#1075000
1!
b00000000000000000000000000010101 #
b00000000000000000000000000010101 $
#1100000
0!
#1125000
1!
b00000000000000000000000000010110 #
b00000000000000000000000000010110 $
#1150000
0!
#1175000
1!
b00000000000000000000000000010111 #
b00000000000000000000000000010111 $
#1200000
0!
#1225000
1!
b00000000000000000000000000011000 #
b00000000000000000000000000011000 $
#1250000
0!
#1275000
1!
b00000000000000000000000000011001 #
b00000000000000000000000000011001 $
#1300000
0!
#1325000
1!
b00000000000000000000000000011010 #
b00000000000000000000000000011010 $
#1350000
0!
#1375000
1!
b00000000000000000000000000011011 #
b00000000000000000000000000011011 $
#1400000
0!
#1425000
1!
b00000000000000000000000000011100 #
b00000000000000000000000000011100 $
#1450000
0!
#1475000
1!
b00000000000000000000000000011101 #
b00000000000000000000000000011101 $
#1500000
0!
#1525000
1!
b00000000000000000000000000011110 #
b00000000000000000000000000011110 $
#1550000
0!
#1575000
1!
b00000000000000000000000000011111 #
b00000000000000000000000000011111 $
#1600000
0!
#1625000
1!
b00000000000000000000000000100000 #
b00000000000000000000000000100000 $
#1650000
0!
#1675000
1!
b00000000000000000000000000100001 #
b00000000000000000000000000100001 $
#1700000
0!
#1725000
1!
b00000000000000000000000000100010 #
b00000000000000000000000000100010 $
#1750000
0!
#1775000
1!
b00000000000000000000000000100011 #
b00000000000000000000000000100011 $
#1800000
0!
#1825000
1!
b00000000000000000000000000100100 #
b00000000000000000000000000100100 $
#1850000
0!
#1875000
1!
b00000000000000000000000000100101 #
b00000000000000000000000000100101 $
#1900000
0!
#1925000
1!
b00000000000000000000000000100110 #
b00000000000000000000000000100110 $
#1950000
0!
#1975000
1!
b00000000000000000000000000100111 #
b00000000000000000000000000100111 $
#2000000
0!
#2025000
1!
b00000000000000000000000000101000 #
b00000000000000000000000000101000 $
#2050000
0!
#2075000
1!
b00000000000000000000000000101001 #
b00000000000000000000000000101001 $
#2100000
0!
#2125000
1!
b00000000000000000000000000101010 #
b00000000000000000000000000101010 $
#2150000
0!
#2175000
1!
b00000000000000000000000000101011 #
b00000000000000000000000000101011 $
#2200000
0!
#2225000
1!
b00000000000000000000000000101100 #
b00000000000000000000000000101100 $
#2250000
0!
#2275000
1!
b00000000000000000000000000101101 #
b00000000000000000000000000101101 $
#2300000
0!
#2325000
1!
b00000000000000000000000000101110 #
b00000000000000000000000000101110 $
#2350000
0!
#2375000
1!
b00000000000000000000000000101111 #
b00000000000000000000000000101111 $
#2400000
0!
#2425000
1!
b00000000000000000000000000110000 #
b00000000000000000000000000110000 $
#2450000
0!
#2475000
1!
b00000000000000000000000000110001 #
b00000000000000000000000000110001 $
#2500000
0!
#2525000
1!
b00000000000000000000000000110010 #
b00000000000000000000000000110010 $
#2550000
0!
#2575000
1!
b00000000000000000000000000110011 #
b00000000000000000000000000110011 $
#2600000
0!
#2625000
1!
b00000000000000000000000000110100 #
b00000000000000000000000000110100 $
#2650000
0!
#2675000
1!
b00000000000000000000000000110101 #
b00000000000000000000000000110101 $
#2700000
0!
#2725000
1!
b00000000000000000000000000110110 #
b00000000000000000000000000110110 $
#2750000
0!
#2775000
1!
b00000000000000000000000000110111 #
b00000000000000000000000000110111 $
#2800000
0!
#2825000
1!
b00000000000000000000000000111000 #
b00000000000000000000000000111000 $
#2850000
0!
#2875000
1!
b00000000000000000000000000111001 #
b00000000000000000000000000111001 $
#2900000
0!
#2925000
1!
b00000000000000000000000000111010 #
b00000000000000000000000000111010 $
#2950000
0!
#2975000
1!
b00000000000000000000000000111011 #
b00000000000000000000000000111011 $
#3000000
0!
#3025000
1!
b00000000000000000000000000111100 #
b00000000000000000000000000111100 $
#3050000
0!
#3075000
1!
b00000000000000000000000000111101 #
b00000000000000000000000000111101 $
#3100000
0!
#3125000
1!
b00000000000000000000000000111110 #
b00000000000000000000000000111110 $
#3150000
0!
#3175000
1!
b00000000000000000000000000111111 #
b00000000000000000000000000111111 $
#3200000
0!
#3225000
1!
b00000000000000000000000001000000 #
b00000000000000000000000001000000 $
#3250000
0!
#3275000
1!
b00000000000000000000000001000001 #
b00000000000000000000000001000001 $
#3300000
0!
#3325000
1!
b00000000000000000000000001000010 #
b00000000000000000000000001000010 $
#3350000
0!
#3375000
1!
b00000000000000000000000001000011 #
b00000000000000000000000001000011 $
#3400000
0!
#3425000
1!
b00000000000000000000000001000100 #
b00000000000000000000000001000100 $
#3450000
0!
#3475000
1!
b00000000000000000000000001000101 #
b00000000000000000000000001000101 $
#3500000
0!
#3525000
1!
b00000000000000000000000001000110 #
b00000000000000000000000001000110 $
#3550000
0!
#3575000
1!
b00000000000000000000000001000111 #
b00000000000000000000000001000111 $
#3600000
0!
#3625000
1!
b00000000000000000000000001001000 #
b00000000000000000000000001001000 $
#3650000
0!
#3675000
1!
b00000000000000000000000001001001 #
b00000000000000000000000001001001 $
#3700000
0!
#3725000
1!
b00000000000000000000000001001010 #
b00000000000000000000000001001010 $
#3750000
0!
#3775000
1!
b00000000000000000000000001001011 #
b00000000000000000000000001001011 $
#3800000
0!
#3825000
1!
b00000000000000000000000001001100 #
b00000000000000000000000001001100 $
#3850000
0!
#3875000
1!
b00000000000000000000000001001101 #
b00000000000000000000000001001101 $
#3900000
0!
#3925000
1!
b00000000000000000000000001001110 #
b00000000000000000000000001001110 $
#3950000
0!
#3975000
1!
b00000000000000000000000001001111 #
b00000000000000000000000001001111 $
#4000000
0!
#4025000
1!
b00000000000000000000000001010000 #
b00000000000000000000000001010000 $
#4050000
0!
#4075000
1!
b00000000000000000000000001010001 #
b00000000000000000000000001010001 $
#4100000
0!
#4125000
1!
b00000000000000000000000001010010 #
b00000000000000000000000001010010 $
#4150000
0!
#4175000
1!
b00000000000000000000000001010011 #
b00000000000000000000000001010011 $
#4200000
0!
#4225000
1!
b00000000000000000000000001010100 #
b00000000000000000000000001010100 $
#4250000
0!
#4275000
1!
b00000000000000000000000001010101 #
b00000000000000000000000001010101 $
#4300000
0!
#4325000
1!
b00000000000000000000000001010110 #
b00000000000000000000000001010110 $
#4350000
0!
#4375000
1!
b00000000000000000000000001010111 #
b00000000000000000000000001010111 $
#4400000
0!
#4425000
1!
b00000000000000000000000001011000 #
b00000000000000000000000001011000 $
#4450000
0!
#4475000
1!
b00000000000000000000000001011001 #
b00000000000000000000000001011001 $
#4500000
0!
#4525000
1!
b00000000000000000000000001011010 #
b00000000000000000000000001011010 $
#4550000
0!
#4575000
1!
b00000000000000000000000001011011 #
b00000000000000000000000001011011 $
#4600000
0!
#4625000
1!
b00000000000000000000000001011100 #
b00000000000000000000000001011100 $
#4650000
0!
#4675000
1!
b00000000000000000000000001011101 #
b00000000000000000000000001011101 $
#4700000
0!
#4725000
1!
b00000000000000000000000001011110 #
b00000000000000000000000001011110 $
#4750000
0!
#4775000
1!
b00000000000000000000000001011111 #
b00000000000000000000000001011111 $
#4800000
0!
#4825000
1!
b00000000000000000000000001100000 #
b00000000000000000000000001100000 $
#4850000
0!
#4875000
1!
b00000000000000000000000001100001 #
b00000000000000000000000001100001 $
#4900000
0!
#4925000
1!
b00000000000000000000000001100010 #
b00000000000000000000000001100010 $
#4950000
0!
#4975000
1!
b00000000000000000000000001100011 #
b00000000000000000000000001100011 $
#5000000
0!
#5025000
1!
b00000000000000000000000001100100 #
b00000000000000000000000001100100 $
#5050000
0!
#5075000
1!
b00000000000000000000000001100101 #
b00000000000000000000000001100101 $
#5100000
0!
#5125000
1!
b00000000000000000000000001100110 #
b00000000000000000000000001100110 $
#5150000
0!
#5175000
1!
b00000000000000000000000001100111 #
b00000000000000000000000001100111 $
#5200000
0!
#5225000
1!
b00000000000000000000000001101000 #
b00000000000000000000000001101000 $
#5250000
0!
#5275000
1!
b00000000000000000000000001101001 #
b00000000000000000000000001101001 $
#5300000
0!
#5325000
1!
b00000000000000000000000001101010 #
b00000000000000000000000001101010 $
#5350000
0!
#5375000
1!
b00000000000000000000000001101011 #
b00000000000000000000000001101011 $
#5400000
0!
#5425000
1!
b00000000000000000000000001101100 #
b00000000000000000000000001101100 $
#5450000
0!
#5475000
1!
b00000000000000000000000001101101 #
b00000000000000000000000001101101 $
#5500000
0!
#5525000
1!
b00000000000000000000000001101110 #
b00000000000000000000000001101110 $
#5550000
0!
#5575000
1!
b00000000000000000000000001101111 #
b00000000000000000000000001101111 $
#5600000
0!
#5625000
1!
b00000000000000000000000001110000 #
b00000000000000000000000001110000 $
#5650000
0!
#5675000
1!
b00000000000000000000000001110001 #
b00000000000000000000000001110001 $
#5700000
0!
#5725000
1!
b00000000000000000000000001110010 #
b00000000000000000000000001110010 $
#5750000
0!
#5775000
1!
b00000000000000000000000001110011 #
b00000000000000000000000001110011 $
#5800000
0!
#5825000
1!
b00000000000000000000000001110100 #
b00000000000000000000000001110100 $
#5850000
0!
#5875000
1!
b00000000000000000000000001110101 #
b00000000000000000000000001110101 $
#5900000
0!
#5925000
1!
b00000000000000000000000001110110 #
b00000000000000000000000001110110 $
#5950000
0!
#5975000
1!
b00000000000000000000000001110111 #
b00000000000000000000000001110111 $
#6000000
0!
#6025000
1!
b00000000000000000000000001111000 #
b00000000000000000000000001111000 $
#6050000
0!
#6075000
1!
b00000000000000000000000001111001 #
b00000000000000000000000001111001 $
#6100000
0!
#6125000
1!
b00000000000000000000000001111010 #
b00000000000000000000000001111010 $
#6150000
0!
#6175000
1!
b00000000000000000000000001111011 #
b00000000000000000000000001111011 $
#6200000
0!
#6225000
1!
b00000000000000000000000001111100 #
b00000000000000000000000001111100 $
#6250000
0!
#6275000
1!
b00000000000000000000000001111101 #
b00000000000000000000000001111101 $
#6300000
0!
#6325000
1!
b00000000000000000000000001111110 #
b00000000000000000000000001111110 $
#6350000
0!
#6375000
1!
b00000000000000000000000001111111 #
b00000000000000000000000001111111 $
#6400000
0!
#6425000
1!
b00000000000000000000000010000000 #
b00000000000000000000000010000000 $
#6450000
0!
#6475000
1!
b00000000000000000000000010000001 #
b00000000000000000000000010000001 $
#6500000
0!
#6525000
1!
b00000000000000000000000010000010 #
b00000000000000000000000010000010 $
#6550000
0!
#6575000
1!
b00000000000000000000000010000011 #
b00000000000000000000000010000011 $
#6600000
0!
#6625000
1!
b00000000000000000000000010000100 #
b00000000000000000000000010000100 $
#6650000
0!
#6675000
1!
b00000000000000000000000010000101 #
b00000000000000000000000010000101 $
#6700000
0!
#6725000
1!
b00000000000000000000000010000110 #
b00000000000000000000000010000110 $
#6750000
0!
#6775000
1!
b00000000000000000000000010000111 #
b00000000000000000000000010000111 $
#6800000
0!
#6825000
1!
b00000000000000000000000010001000 #
b00000000000000000000000010001000 $
#6850000
0!
#6875000
1!
b00000000000000000000000010001001 #
b00000000000000000000000010001001 $
#6900000
0!
#6925000
1!
b00000000000000000000000010001010 #
b00000000000000000000000010001010 $
#6950000
0!
#6975000
1!
b00000000000000000000000010001011 #
b00000000000000000000000010001011 $
#7000000
0!
#7025000
1!
b00000000000000000000000010001100 #
b00000000000000000000000010001100 $
#7050000
0!
#7075000
1!
b00000000000000000000000010001101 #
b00000000000000000000000010001101 $
#7100000
0!
#7125000
1!
b00000000000000000000000010001110 #
b00000000000000000000000010001110 $
#7150000
0!
#7175000
1!
b00000000000000000000000010001111 #
b00000000000000000000000010001111 $
#7200000
0!
#7225000
1!
b00000000000000000000000010010000 #
b00000000000000000000000010010000 $
#7250000
0!
#7275000
1!
b00000000000000000000000010010001 #
b00000000000000000000000010010001 $
#7300000
0!
#7325000
1!
b00000000000000000000000010010010 #
b00000000000000000000000010010010 $
#7350000
0!
#7375000
1!
b00000000000000000000000010010011 #
b00000000000000000000000010010011 $
#7400000
0!
#7425000
1!
b00000000000000000000000010010100 #
b00000000000000000000000010010100 $
#7450000
0!
#7475000
1!
b00000000000000000000000010010101 #
b00000000000000000000000010010101 $
#7500000
0!
#7525000
1!
b00000000000000000000000010010110 #
b00000000000000000000000010010110 $
#7550000
0!
#7575000
1!
b00000000000000000000000010010111 #
b00000000000000000000000010010111 $
#7600000
0!
#7625000
1!
b00000000000000000000000010011000 #
b00000000000000000000000010011000 $
#7650000
0!
#7675000
1!
b00000000000000000000000010011001 #
b00000000000000000000000010011001 $
#7700000
0!
#7725000
1!
b00000000000000000000000010011010 #
b00000000000000000000000010011010 $
#7750000
0!
#7775000
1!
b00000000000000000000000010011011 #
b00000000000000000000000010011011 $
#7800000
0!
#7825000
1!
b00000000000000000000000010011100 #
b00000000000000000000000010011100 $
#7850000
0!
#7875000
1!
b00000000000000000000000010011101 #
b00000000000000000000000010011101 $
#7900000
0!
#7925000
1!
b00000000000000000000000010011110 #
b00000000000000000000000010011110 $
#7950000
0!
#7975000
1!
b00000000000000000000000010011111 #
b00000000000000000000000010011111 $
#8000000
0!
#8025000
1!
b00000000000000000000000010100000 #
b00000000000000000000000010100000 $
#8050000
0!
#8075000
1!
b00000000000000000000000010100001 #
b00000000000000000000000010100001 $
#8100000
0!
#8125000
1!
b00000000000000000000000010100010 #
b00000000000000000000000010100010 $
#8150000
0!
#8175000
1!
b00000000000000000000000010100011 #
b00000000000000000000000010100011 $
#8200000
0!
#8225000
1!
b00000000000000000000000010100100 #
b00000000000000000000000010100100 $
#8250000
0!
#8275000
1!
b00000000000000000000000010100101 #
b00000000000000000000000010100101 $
#8300000
0!
#8325000
1!
b00000000000000000000000010100110 #
b00000000000000000000000010100110 $
#8350000
0!
#8375000
1!
b00000000000000000000000010100111 #
b00000000000000000000000010100111 $
#8400000
0!
#8425000
1!
b00000000000000000000000010101000 #
b00000000000000000000000010101000 $
#8450000
0!
#8475000
1!
b00000000000000000000000010101001 #
b00000000000000000000000010101001 $
#8500000
0!
#8525000
1!
b00000000000000000000000010101010 #
b00000000000000000000000010101010 $
#8550000
0!
#8575000
1!
b00000000000000000000000010101011 #
b00000000000000000000000010101011 $
#8600000
0!
#8625000
1!
b00000000000000000000000010101100 #
b00000000000000000000000010101100 $
#8650000
0!
#8675000
1!
b00000000000000000000000010101101 #
b00000000000000000000000010101101 $
#8700000
0!
#8725000
1!
b00000000000000000000000010101110 #
b00000000000000000000000010101110 $
#8750000
0!
#8775000
1!
b00000000000000000000000010101111 #
b00000000000000000000000010101111 $
#8800000
0!
#8825000
1!
b00000000000000000000000010110000 #
b00000000000000000000000010110000 $
#8850000
0!
#8875000
1!
b00000000000000000000000010110001 #
b00000000000000000000000010110001 $
#8900000
0!
#8925000
1!
b00000000000000000000000010110010 #
b00000000000000000000000010110010 $
#8950000
0!
#8975000
1!
b00000000000000000000000010110011 #
b00000000000000000000000010110011 $
#9000000
0!
#9025000
1!
b00000000000000000000000010110100 #
b00000000000000000000000010110100 $
#9050000
0!
#9075000
1!
b00000000000000000000000010110101 #
b00000000000000000000000010110101 $
#9100000
0!
#9125000
1!
b00000000000000000000000010110110 #
b00000000000000000000000010110110 $
#9150000
0!
#9175000
1!
b00000000000000000000000010110111 #
b00000000000000000000000010110111 $
#9200000
0!
#9225000
1!
b00000000000000000000000010111000 #
b00000000000000000000000010111000 $
#9250000
0!
#9275000
1!
b00000000000000000000000010111001 #
b00000000000000000000000010111001 $
#9300000
0!
#9325000
1!
b00000000000000000000000010111010 #
b00000000000000000000000010111010 $
#9350000
0!
#9375000
1!
b00000000000000000000000010111011 #
b00000000000000000000000010111011 $
#9400000
0!
#9425000
1!
b00000000000000000000000010111100 #
b00000000000000000000000010111100 $
#9450000
0!
#9475000
1!
b00000000000000000000000010111101 #
b00000000000000000000000010111101 $
#9500000
0!
#9525000
1!
b00000000000000000000000010111110 #
b00000000000000000000000010111110 $
#9550000
0!
#9575000
1!
b00000000000000000000000010111111 #
b00000000000000000000000010111111 $
#9600000
0!
#9625000
1!
b00000000000000000000000011000000 #
b00000000000000000000000011000000 $
#9650000
0!
#9675000
1!
b00000000000000000000000011000001 #
b00000000000000000000000011000001 $
#9700000
0!
#9725000
1!
b00000000000000000000000011000010 #
b00000000000000000000000011000010 $
#9750000
0!
#9775000
1!
b00000000000000000000000011000011 #
b00000000000000000000000011000011 $
#9800000
0!
#9825000
1!
b00000000000000000000000011000100 #
b00000000000000000000000011000100 $
#9850000
0!
#9875000
1!
b00000000000000000000000011000101 #
b00000000000000000000000011000101 $
#9900000
0!
#9925000
1!
b00000000000000000000000011000110 #
b00000000000000000000000011000110 $
#9950000
0!
#9975000
1!
b00000000000000000000000011000111 #
b00000000000000000000000011000111 $
#10000000
0!
#10025000
1!
b00000000000000000000000011001000 #
b00000000000000000000000011001000 $
#10050000
0!
#10075000
1!
b00000000000000000000000011001001 #
b00000000000000000000000011001001 $
#10100000
0!
#10125000
1!
b00000000000000000000000011001010 #
b00000000000000000000000011001010 $
#10150000
0!
#10175000
1!
b00000000000000000000000011001011 #
b00000000000000000000000011001011 $
#10200000
0!
#10225000
1!
b00000000000000000000000011001100 #
b00000000000000000000000011001100 $
#10250000
0!
#10275000
1!
b00000000000000000000000011001101 #
b00000000000000000000000011001101 $
#10300000
0!
#10325000
1!
b00000000000000000000000011001110 #
b00000000000000000000000011001110 $
#10350000
0!
#10375000
1!
b00000000000000000000000011001111 #
b00000000000000000000000011001111 $
#10400000
0!
#10425000
1!
b00000000000000000000000011010000 #
b00000000000000000000000011010000 $
#10450000
0!
#10475000
1!
b00000000000000000000000011010001 #
b00000000000000000000000011010001 $
#10500000
0!
#10525000
1!
b00000000000000000000000011010010 #
b00000000000000000000000011010010 $
#10550000
0!
#10575000
1!
b00000000000000000000000011010011 #
b00000000000000000000000011010011 $
#10600000
0!
#10625000
1!
b00000000000000000000000011010100 #
b00000000000000000000000011010100 $
#10650000
0!
#10675000
1!
b00000000000000000000000011010101 #
b00000000000000000000000011010101 $
#10700000
0!
#10725000
1!
b00000000000000000000000011010110 #
b00000000000000000000000011010110 $
#10750000
0!
#10775000
1!
b00000000000000000000000011010111 #
b00000000000000000000000011010111 $
#10800000
0!
#10825000
1!
b00000000000000000000000011011000 #
b00000000000000000000000011011000 $
#10850000
0!
#10875000
1!
b00000000000000000000000011011001 #
b00000000000000000000000011011001 $
#10900000
0!
#10925000
1!
b00000000000000000000000011011010 #
b00000000000000000000000011011010 $
#10950000
0!
#10975000
1!
b00000000000000000000000011011011 #
b00000000000000000000000011011011 $
#11000000
0!
#11025000
1!
b00000000000000000000000011011100 #
b00000000000000000000000011011100 $
#11050000
0!
#11075000
1!
b00000000000000000000000011011101 #
b00000000000000000000000011011101 $
#11100000
0!
#11125000
1!
b00000000000000000000000011011110 #
b00000000000000000000000011011110 $
#11150000
0!
#11175000
1!
b00000000000000000000000011011111 #
b00000000000000000000000011011111 $
#11200000
0!
#11225000
1!
b00000000000000000000000011100000 #
b00000000000000000000000011100000 $
#11250000
0!
#11275000
1!
b00000000000000000000000011100001 #
b00000000000000000000000011100001 $
#11300000
0!
#11325000
1!
b00000000000000000000000011100010 #
b00000000000000000000000011100010 $
#11350000
0!
#11375000
1!
b00000000000000000000000011100011 #
b00000000000000000000000011100011 $
#11400000
0!
#11425000
1!
b00000000000000000000000011100100 #
b00000000000000000000000011100100 $
#11450000
0!
#11475000
1!
b00000000000000000000000011100101 #
b00000000000000000000000011100101 $
#11500000
0!
#11525000
1!
b00000000000000000000000011100110 #
b00000000000000000000000011100110 $
#11550000
0!
#11575000
1!
b00000000000000000000000011100111 #
b00000000000000000000000011100111 $
#11600000
0!
#11625000
1!
b00000000000000000000000011101000 #
b00000000000000000000000011101000 $
#11650000
0!
#11675000
1!
b00000000000000000000000011101001 #
b00000000000000000000000011101001 $
#11700000
0!
#11725000
1!
b00000000000000000000000011101010 #
b00000000000000000000000011101010 $
#11750000
0!
#11775000
1!
b00000000000000000000000011101011 #
b00000000000000000000000011101011 $
#11800000
0!
#11825000
1!
b00000000000000000000000011101100 #
b00000000000000000000000011101100 $
#11850000
0!
#11875000
1!
b00000000000000000000000011101101 #
b00000000000000000000000011101101 $
#11900000
0!
#11925000
1!
b00000000000000000000000011101110 #
b00000000000000000000000011101110 $
#11950000
0!
#11975000
1!
b00000000000000000000000011101111 #
b00000000000000000000000011101111 $
#12000000
0!
#12025000
1!
b00000000000000000000000011110000 #
b00000000000000000000000011110000 $
#12050000
0!
#12075000
1!
b00000000000000000000000011110001 #
b00000000000000000000000011110001 $
#12100000
0!
#12125000
1!
b00000000000000000000000011110010 #
b00000000000000000000000011110010 $
#12150000
0!
#12175000
1!
b00000000000000000000000011110011 #
b00000000000000000000000011110011 $
#12200000
0!
#12225000
1!
b00000000000000000000000011110100 #
b00000000000000000000000011110100 $
#12250000
0!
#12275000
1!
b00000000000000000000000011110101 #
b00000000000000000000000011110101 $
#12300000
0!
#12325000
1!
b00000000000000000000000011110110 #
b00000000000000000000000011110110 $
#12350000
0!
#12375000
1!
b00000000000000000000000011110111 #
b00000000000000000000000011110111 $
#12400000
0!
#12425000
1!
b00000000000000000000000011111000 #
b00000000000000000000000011111000 $
#12450000
0!
#12475000
1!
b00000000000000000000000011111001 #
b00000000000000000000000011111001 $
#12500000
0!
#12525000
1!
b00000000000000000000000011111010 #
b00000000000000000000000011111010 $
#12550000
0!
#12575000
1!
b00000000000000000000000011111011 #
b00000000000000000000000011111011 $
#12600000
0!
#12625000
1!
b00000000000000000000000011111100 #
b00000000000000000000000011111100 $
#12650000
0!
#12675000
1!
b00000000000000000000000011111101 #
b00000000000000000000000011111101 $
#12700000
0!
#12725000
1!
b00000000000000000000000011111110 #
b00000000000000000000000011111110 $
#12750000
0!
#12775000
1!
b00000000000000000000000011111111 #
b00000000000000000000000011111111 $
#12800000
0!
#12825000
1!
b00000000000000000000000100000000 #
b00000000000000000000000100000000 $
